wecombot/__init__.py
wecombot/__version__.py
wecombot/bot.py
wecombot/errors.py
wecombot/log.py
WecomBot-0.1.0.dist-info/LICENSE
WecomBot-0.1.0.dist-info/METADATA
WecomBot-0.1.0.dist-info/WHEEL
WecomBot-0.1.0.dist-info/top_level.txt
WecomBot-0.1.0.dist-info/RECORD
